multi_model_debate/__init__.py
multi_model_debate/__main__.py
multi_model_debate/cli.py
multi_model_debate/config.py
multi_model_debate/exceptions.py
multi_model_debate/orchestrator.py
multi_model_debate/pre_debate.py
multi_model_debate/response_parser.py
multi_model_debate/roles.py
multi_model_debate/models/__init__.py
multi_model_debate/models/claude.py
multi_model_debate/models/cli_wrapper.py
multi_model_debate/models/gemini.py
multi_model_debate/models/openai.py
multi_model_debate/models/protocols.py
multi_model_debate/phases/__init__.py
multi_model_debate/phases/base.py
multi_model_debate/phases/baseline.py
multi_model_debate/phases/debate.py
multi_model_debate/phases/defense.py
multi_model_debate/phases/final_position.py
multi_model_debate/phases/judge.py
multi_model_debate/phases/synthesis.py
multi_model_debate/prompts/arbiter_prompt.md.j2
multi_model_debate/prompts/arbiter_summary.md.j2
multi_model_debate/prompts/baseline_critique.md.j2
multi_model_debate/prompts/critic_1_lens.md.j2
multi_model_debate/prompts/critic_2_lens.md.j2
multi_model_debate/prompts/debate_round.md.j2
multi_model_debate/prompts/defense_initial.md.j2
multi_model_debate/prompts/defense_round.md.j2
multi_model_debate/prompts/judge.md.j2
multi_model_debate/prompts/judge_prompt.md.j2
multi_model_debate/prompts/strategist_proxy_lens.md.j2
multi_model_debate/prompts/synthesis_prompt.md.j2
multi_model_debate/prompts/synthesis_template.md.j2
multi_model_debate/prompts/winner_response.md.j2
multi_model_debate/storage/__init__.py
multi_model_debate/storage/run.py
multi_model_debate-1.0.1.dist-info/METADATA
multi_model_debate-1.0.1.dist-info/WHEEL
multi_model_debate-1.0.1.dist-info/entry_points.txt
multi_model_debate-1.0.1.dist-info/licenses/LICENSE
multi_model_debate-1.0.1.dist-info/RECORD
